LICENSE
MANIFEST.in
README.md
setup.cfg
setup.py
django2_rest_passwordreset.egg-info/PKG-INFO
django2_rest_passwordreset.egg-info/SOURCES.txt
django2_rest_passwordreset.egg-info/dependency_links.txt
django2_rest_passwordreset.egg-info/top_level.txt
django_rest_passwordreset/__init__.py
django_rest_passwordreset/admin.py
django_rest_passwordreset/models.py
django_rest_passwordreset/serializers.py
django_rest_passwordreset/signals.py
django_rest_passwordreset/urls.py
django_rest_passwordreset/utils.py
django_rest_passwordreset/views.py
django_rest_passwordreset/migrations/0001_initial.py
django_rest_passwordreset/migrations/0002_pk_migration.py
django_rest_passwordreset/migrations/0003_resetpasswordtoken_used.py
django_rest_passwordreset/migrations/0004_resetpasswordtoken_expired.py
django_rest_passwordreset/migrations/0005_auto_20181017_1513.py
django_rest_passwordreset/migrations/0006_resetpasswordtoken_is_long_token.py
django_rest_passwordreset/migrations/__init__.py
docs/.gitkeep
tests/__init__.py
tests/manage.py
tests/settings.py
tests/test.py
tests/urls.py